sitemap_builder/__init__.py
sitemap_builder/sitemap.py
sitemap_builder/tests/__init__.py
sitemap_builder/tests/test_basic.py
sitemap_builder-0.0.1.dist-info/METADATA
sitemap_builder-0.0.1.dist-info/RECORD
sitemap_builder-0.0.1.dist-info/WHEEL
sitemap_builder-0.0.1.dist-info/top_level.txt
