Metadata-Version: 2.1
Name: sitemap-builder
Version: 0.0.1
Summary: Generate sitemaps from programmatically collected URLs
Home-page: https://github.com/marcanuy/sitemap-builder
Author: Marcelo Canina
Author-email: me@marcanuy.com
License: UNKNOWN
Platform: UNKNOWN
Classifier: Programming Language :: Python :: 3
Classifier: License :: OSI Approved :: MIT License
Classifier: Operating System :: OS Independent
